undoom_douyin_data_analysis/__init__.py
undoom_douyin_data_analysis/douyin_mcp_server.py
iflow_mcp_undoom_douyin_data_analysis-0.1.3.dist-info/METADATA
iflow_mcp_undoom_douyin_data_analysis-0.1.3.dist-info/WHEEL
iflow_mcp_undoom_douyin_data_analysis-0.1.3.dist-info/entry_points.txt
iflow_mcp_undoom_douyin_data_analysis-0.1.3.dist-info/licenses/LICENSE
iflow_mcp_undoom_douyin_data_analysis-0.1.3.dist-info/RECORD
