Metadata-Version: 2.4
Name: iflow-mcp_undoom-douyin-data-analysis
Version: 0.1.3
Summary: 抖音数据分析 MCP 服务器 - 提供抖音视频和用户数据的采集、分析和导出功能
Project-URL: Homepage, https://github.com/kk520879/undoom-douyin-data-analysis
Project-URL: Repository, https://github.com/kk520879/undoom-douyin-data-analysis
Project-URL: Issues, https://github.com/kk520879/undoom-douyin-data-analysis/issues
Author-email: undoom <kaikaihuhu666@163.com>
License-File: LICENSE
Keywords: data-analysis,douyin,mcp,tiktok,web-scraping
Classifier: Development Status :: 4 - Beta
Classifier: Intended Audience :: Developers
Classifier: License :: OSI Approved :: MIT License
Classifier: Programming Language :: Python :: 3
Classifier: Programming Language :: Python :: 3.10
Classifier: Programming Language :: Python :: 3.11
Classifier: Programming Language :: Python :: 3.12
Classifier: Programming Language :: Python :: 3.13
Requires-Python: >=3.10
Requires-Dist: beautifulsoup4>=4.12.0
Requires-Dist: drissionpage>=4.0.0
Requires-Dist: jieba>=0.42.1
Requires-Dist: lxml>=4.9.0
Requires-Dist: mcp[cli]>=1.12.4
Requires-Dist: openpyxl>=3.1.0
Requires-Dist: pandas>=2.0.0
Requires-Dist: requests>=2.31.0
